MANIFEST.in
README.txt
setup.py
docs/HISTORY.txt
docs/INSTALL.txt
docs/LICENSE.GPL
docs/LICENSE.txt
monet/__init__.py
monet.recurring_event.egg-info/PKG-INFO
monet.recurring_event.egg-info/SOURCES.txt
monet.recurring_event.egg-info/dependency_links.txt
monet.recurring_event.egg-info/entry_points.txt
monet.recurring_event.egg-info/namespace_packages.txt
monet.recurring_event.egg-info/not-zip-safe
monet.recurring_event.egg-info/requires.txt
monet.recurring_event.egg-info/top_level.txt
monet/recurring_event/README.txt
monet/recurring_event/__init__.py
monet/recurring_event/config.py
monet/recurring_event/configure.zcml
monet/recurring_event/interfaces.py
monet/recurring_event/setuphandlers.py
monet/recurring_event/Extensions/install.py
monet/recurring_event/profiles/default/browserlayer.xml
monet/recurring_event/profiles/default/metadata.xml
monet/recurring_event/profiles/uninstall/browserlayer.xml
monet/recurring_event/profiles/uninstall/import_steps.xml
monet/recurring_event/profiles/uninstall/monet.recurring_event-uninstall.txt