Metadata-Version: 1.0
Name: monet.recurring-event
Version: 0.7.0
Summary: Old event type for Plone (use only for remove older versions of this package)
Home-page: http://plone.comune.modena.it/svn/monet/monet.recurring_event
Author: RedTurtle Technology
Author-email: sviluppoplone@redturtle.it
License: GPL
Platform: UNKNOWN
Classifier: Framework :: Plone
Classifier: Programming Language :: Python
Classifier: Development Status :: 7 - Inactive
Classifier: License :: OSI Approved :: GNU General Public License (GPL)
